setup.py
AmqpConnector/__init__.py
AmqpConnector.egg-info/PKG-INFO
AmqpConnector.egg-info/SOURCES.txt
AmqpConnector.egg-info/dependency_links.txt
AmqpConnector.egg-info/pbr.json
AmqpConnector.egg-info/requires.txt
AmqpConnector.egg-info/top_level.txt