Metadata-Version: 1.0
Name: AmqpConnector
Version: 0.0.40
Summary: Simple library for building a distributed task system over AMQP.
Home-page: http://pypi.python.org/pypi/AmqpConnector/
Author: Connor Wolf
Author-email: github@imaginaryindustries.com
License: UNKNOWN
Platform: UNKNOWN
